mymemory_tr/__init__.py
mymemory_tr/mymemory_tr.py
tests/__init__.py
tests/test_mymemory_tr.py
tests/test_sanity.py
memory_tr_free-0.0.1.dist-info/LICENSE
memory_tr_free-0.0.1.dist-info/METADATA
memory_tr_free-0.0.1.dist-info/WHEEL
memory_tr_free-0.0.1.dist-info/top_level.txt
memory_tr_free-0.0.1.dist-info/RECORD
