Metadata-Version: 2.1
Name: memory-tr-free
Version: 0.0.1
Summary: translate for free with async and proxy support
Home-page: http://github.com/ffreemt/memory-tr-free
Author: mikeee
License: MIT License
Download-URL: https://github.com/ffreemt/memory-tr-free/archive/v_001.tar.gz
Keywords: machine translation,free,async
Platform: UNKNOWN
Classifier: Development Status :: 3 - Alpha
Classifier: Intended Audience :: Developers
Classifier: Programming Language :: Python :: 3
Classifier: Programming Language :: Python :: 3.6
Classifier: License :: OSI Approved :: MIT License
Requires-Dist: httpx
Requires-Dist: loguru
